baobaxia_publica-0.1.16.dist-info/licenses/LICENSE
publica/__init__.py
publica/cli.py
baobaxia_publica-0.1.16.dist-info/METADATA
baobaxia_publica-0.1.16.dist-info/WHEEL
baobaxia_publica-0.1.16.dist-info/entry_points.txt
baobaxia_publica-0.1.16.dist-info/top_level.txt
baobaxia_publica-0.1.16.dist-info/RECORD
