Metadata-Version: 2.4
Name: baobaxia-publica
Version: 0.1.16
Summary: Ferramenta de linha de comando para publicar mídias e artigos no Baobáxia
Author-email: NPDD/Rede Mocambos <npdd@mocambos.net>
License-Expression: GPL-3.0
Requires-Python: >=3.8
License-File: LICENSE
Requires-Dist: requests
Requires-Dist: tqdm
Requires-Dist: urllib3
Dynamic: license-file
